napalm_aos/__init__.py
napalm_aos/aos.py
napalm_aos/utils/AlcatelOS.py
napalm_aos/utils/__init__.py
napalm_aos/utils/utils.py
napalm_aos-0.3.0.dist-info/DESCRIPTION.rst
napalm_aos-0.3.0.dist-info/METADATA
napalm_aos-0.3.0.dist-info/RECORD
napalm_aos-0.3.0.dist-info/WHEEL
napalm_aos-0.3.0.dist-info/metadata.json
napalm_aos-0.3.0.dist-info/top_level.txt
