Metadata-Version: 2.0
Name: napalm-aos
Version: 0.3.0
Summary: Network Automation and Programmability Abstraction Layer with Multivendor support
Home-page: https://github.com/napalm-automation/napalm-aos
Author: Alcatel Lucent Enterprise
Author-email: ebg_global_supportcenter@al-enterprise.com
License: UNKNOWN
Platform: UNKNOWN
Classifier: Topic :: Utilities
Classifier: Programming Language :: Python
Classifier: Programming Language :: Python :: 3
Classifier: Programming Language :: Python :: 3.6
Classifier: Operating System :: POSIX :: Linux
Classifier: Operating System :: MacOS
Requires-Dist: napalm (>=3.0.1)
Requires-Dist: paramiko (>=2.4.0)
Requires-Dist: scp (>=0.10.2)
